{
  "id": "IMAGE",
  "label": "Image Loader",
  "category": "Source",
  "description": "Loads an external image texture. Optional UV input.",
  "locales": {
    "zh": {
      "Image Loader": "图片加载器",
      "Loads an external image texture. Optional UV input.": "加载外部图片纹理。可选 UV 输入。",
      "image": "图片"
    }
  },
  "data": {
    "glsl": "void run(vec2 uv, vec2 uv_in, sampler2D image, out vec4 result) {\n  vec2 coord = (uv_in == vec2(0.0)) ? uv : uv_in;\n  result = texture2D(image, coord);\n}",
    "inputs": [
      { "id": "uv_in", "name": "uv_in", "type": "vec2" },
      { "id": "image", "name": "image", "type": "sampler2D" }
    ],
    "outputType": "vec4",
    "outputs": [{ "id": "result", "name": "result", "type": "vec4" }],
    "uniforms": {
      "uv_in": { "type": "vec2", "value": [0,0] },
      "image": { "type": "sampler2D", "value": null }
    }
  }
}